tafrigh/__init__.py
tafrigh/audio_splitter.py
tafrigh/cli.py
tafrigh/config.py
tafrigh/downloader.py
tafrigh/recognizers/__init__.py
tafrigh/recognizers/whisper_recognizer.py
tafrigh/recognizers/wit_calling_throttle.py
tafrigh/recognizers/wit_recognizer.py
tafrigh/types/__init__.py
tafrigh/types/segment_type.py
tafrigh/types/transcript_type.py
tafrigh/types/whisper/__init__.py
tafrigh/types/whisper/type_hints.py
tafrigh/utils/__init__.py
tafrigh/utils/cli_utils.py
tafrigh/utils/file_utils.py
tafrigh/utils/time_utils.py
tafrigh/utils/whisper/__init__.py
tafrigh/utils/whisper/whisper_utils.py
tafrigh/utils/wit/__init__.py
tafrigh/utils/wit/file_utils.py
tafrigh/writer.py
tafrigh-1.7.6.dist-info/LICENSE
tafrigh-1.7.6.dist-info/METADATA
tafrigh-1.7.6.dist-info/WHEEL
tafrigh-1.7.6.dist-info/entry_points.txt
tafrigh-1.7.6.dist-info/RECORD
