Metadata-Version: 2.3
Name: tafrigh
Version: 1.7.6
Summary: تفريغ النصوص وإنشاء ملفات SRT و VTT باستخدام نماذج Whisper وتقنية wit.ai.
License: MIT
Keywords: tafrigh,speech-to-text,wit.ai,whisper
Author: EasyBooks
Author-email: easybooksdev@gmail.com
Requires-Python: >=3.10
Classifier: Development Status :: 5 - Production/Stable
Classifier: Intended Audience :: Developers
Classifier: Intended Audience :: Education
Classifier: Intended Audience :: Science/Research
Classifier: License :: OSI Approved :: MIT License
Classifier: Operating System :: OS Independent
Classifier: Programming Language :: Python :: 3
Classifier: Programming Language :: Python :: 3.10
Classifier: Programming Language :: Python :: 3.11
Classifier: Programming Language :: Python :: 3.12
Classifier: Programming Language :: Python :: 3.13
Classifier: Topic :: Scientific/Engineering :: Artificial Intelligence
Provides-Extra: all
Provides-Extra: whisper
Provides-Extra: wit
Requires-Dist: auditok (>=0.3.0) ; extra == "wit"
Requires-Dist: faster-whisper (>=1.1.0) ; extra == "whisper"
Requires-Dist: numba (>=0.60.0)
Requires-Dist: openai-whisper (>=20240930) ; extra == "whisper"
Requires-Dist: pydub (>=0.25.1) ; extra == "wit"
Requires-Dist: requests (>=2.32.0) ; extra == "wit"
Requires-Dist: stable-ts (>=2.19.0) ; extra == "whisper"
Requires-Dist: tqdm (>=4.67.1)
Requires-Dist: yt-dlp[default] (>=2025.3.31,<2026.0.0)
Project-URL: Homepage, https://tafrigh.ieasybooks.com
Project-URL: Repository, https://github.com/ieasybooks/tafrigh
